hdsemg_shared/__init__.py
hdsemg_shared/fileio/__init__.py
hdsemg_shared/fileio/file_io.py
hdsemg_shared/fileio/matlab_file_io.py
hdsemg_shared/fileio/otb_4_file_io.py
hdsemg_shared/fileio/otb_plus_file_io.py
hdsemg_shared/filters/__init__.py
hdsemg_shared/filters/bandpass.py
hdsemg_shared/preprocessing/__init__.py
hdsemg_shared/preprocessing/differential.py
hdsemg_shared-0.11.1.dist-info/METADATA
hdsemg_shared-0.11.1.dist-info/WHEEL
hdsemg_shared-0.11.1.dist-info/top_level.txt
hdsemg_shared-0.11.1.dist-info/RECORD
