Metadata-Version: 2.4
Name: hdsemg-shared
Version: 0.11.1
Summary: Utility Methods for hd-semg files.
Home-page: https://johanneskasser.github.io/hdsemg-shared/
Author: Johannes Kasser
Author-email: johanneskasser@outlook.de
Classifier: Programming Language :: Python :: 3
Classifier: Operating System :: OS Independent
Requires-Python: >=3.8
Requires-Dist: numpy
Requires-Dist: scipy
Dynamic: author
Dynamic: author-email
Dynamic: classifier
Dynamic: description
Dynamic: description-content-type
Dynamic: home-page
Dynamic: requires-dist
Dynamic: requires-python
Dynamic: summary
